iso/__init__.py
iso/__version__.py
iso/iso3166.py
iso/iso4217.py
iso/utils.py
iso/data/3166_1.csv
iso/data/3166_2_DO.csv
iso/data/4217.csv
snatsch_iso-0.1.2.dist-info/LICENSE.txt
snatsch_iso-0.1.2.dist-info/METADATA
snatsch_iso-0.1.2.dist-info/WHEEL
snatsch_iso-0.1.2.dist-info/top_level.txt
snatsch_iso-0.1.2.dist-info/RECORD
