Metadata-Version: 2.1
Name: snatsch-iso
Version: 0.1.2
Summary: A lightweight python library to retrieve countries and currencies based on ISO_3166-1 and ISO_4217 standards.
Home-page: https://github.com/snatsch/python-iso
Author: Victor Natschke
Author-email: vnatschke@gmail.com
License: MIT
Keywords: iso iso4217 iso3166
Classifier: Programming Language :: Python :: 3.8
Classifier: Programming Language :: Python :: 3.9
Classifier: Programming Language :: Python :: 3.10
Classifier: Programming Language :: Python :: 3.11
Classifier: Programming Language :: Python :: 3.12
License-File: LICENSE.txt
